object_detect/__init__.py
object_detect/version.txt
object_detect/yolo5.onnx
object_detect-0.0.5.dist-info/METADATA
object_detect-0.0.5.dist-info/WHEEL
object_detect-0.0.5.dist-info/top_level.txt
object_detect-0.0.5.dist-info/RECORD
